Metadata-Version: 1.0
Name: envaws
Version: 0.1
Summary: Run application with environment loaded from AWS SSM.
Home-page: https://github.com/and3rson/envaws
Author: Andrew Dunai
Author-email: a@dun.ai
License: UNKNOWN
Platform: UNKNOWN
